setup.py
Sergi0/Binomialdistribution.py
Sergi0/Gaussiandistribution.py
Sergi0/Generaldistribution.py
Sergi0/__init__.py
Sergi0.egg-info/PKG-INFO
Sergi0.egg-info/SOURCES.txt
Sergi0.egg-info/dependency_links.txt
Sergi0.egg-info/not-zip-safe
Sergi0.egg-info/top_level.txt