Metadata-Version: 1.0
Name: Sergi0
Version: 0.1
Summary: Gaussian and Binomial distributions
Home-page: UNKNOWN
Author: Y.A alias sergio
Author-email: UNKNOWN
License: UNKNOWN
Platform: UNKNOWN
